setup.py
udacityDistributionEMC/Binomialdistribution.py
udacityDistributionEMC/Gaussiandistribution.py
udacityDistributionEMC/Generaldistribution.py
udacityDistributionEMC/__init__.py
udacityDistributionEMC.egg-info/PKG-INFO
udacityDistributionEMC.egg-info/SOURCES.txt
udacityDistributionEMC.egg-info/dependency_links.txt
udacityDistributionEMC.egg-info/not-zip-safe
udacityDistributionEMC.egg-info/top_level.txt