Metadata-Version: 1.0
Name: udacityDistributionEMC
Version: 0.1
Summary: Gaussian & Binomial distributions
Home-page: UNKNOWN
Author: Eoghan McCarey
Author-email: UNKNOWN
License: UNKNOWN
Platform: UNKNOWN
